ai/backend/krunner/ubuntu/__init__.py
ai/backend/krunner/ubuntu/krunner-env.ubuntu16.04.dockerfile
ai/backend/krunner/ubuntu/krunner-env.ubuntu16.04.x86_64.tar.xz
ai/backend/krunner/ubuntu/krunner-env.ubuntu18.04.dockerfile
ai/backend/krunner/ubuntu/krunner-env.ubuntu18.04.x86_64.tar.xz
ai/backend/krunner/ubuntu/krunner-env.ubuntu20.04.dockerfile
ai/backend/krunner/ubuntu/krunner-env.ubuntu20.04.x86_64.tar.xz
ai/backend/krunner/ubuntu/krunner-python.ubuntu16.04.dockerfile
ai/backend/krunner/ubuntu/krunner-python.ubuntu16.04.txt
ai/backend/krunner/ubuntu/krunner-python.ubuntu18.04.dockerfile
ai/backend/krunner/ubuntu/krunner-python.ubuntu18.04.txt
ai/backend/krunner/ubuntu/krunner-python.ubuntu20.04.dockerfile
ai/backend/krunner/ubuntu/krunner-python.ubuntu20.04.txt
ai/backend/krunner/ubuntu/krunner-version.ubuntu16.04.txt
ai/backend/krunner/ubuntu/krunner-version.ubuntu18.04.txt
ai/backend/krunner/ubuntu/krunner-version.ubuntu20.04.txt
ai/backend/krunner/ubuntu/plugin.py
ai/backend/krunner/ubuntu/requirements.txt
ai/backend/krunner/ubuntu/ttyd_linux.x86_64.bin
ai/backend/krunner/ubuntu/versions.txt
backend.ai_krunner_ubuntu-3.5.0.dist-info/LICENSE
backend.ai_krunner_ubuntu-3.5.0.dist-info/METADATA
backend.ai_krunner_ubuntu-3.5.0.dist-info/WHEEL
backend.ai_krunner_ubuntu-3.5.0.dist-info/entry_points.txt
backend.ai_krunner_ubuntu-3.5.0.dist-info/top_level.txt
backend.ai_krunner_ubuntu-3.5.0.dist-info/RECORD
